mixiu_pytest_helper/__init__.py
mixiu_pytest_helper/annotation.py
mixiu_pytest_helper/base_test.py
mixiu_pytest_helper/collector.py
mixiu_pytest_helper/config.py
mixiu_pytest_helper/conftest.py
mixiu_pytest_helper/context.py
mixiu_pytest_helper/dir.py
mixiu_pytest_helper/infrastructure.py
mixiu_pytest_helper/log.py
mixiu_pytest_helper/repository.py
mixiu_pytest_helper/run.py
mixiu_pytest_helper-0.7.1.dist-info/LICENSE
mixiu_pytest_helper-0.7.1.dist-info/METADATA
mixiu_pytest_helper-0.7.1.dist-info/WHEEL
mixiu_pytest_helper-0.7.1.dist-info/top_level.txt
mixiu_pytest_helper-0.7.1.dist-info/RECORD
