Metadata-Version: 2.1
Name: mixiu-pytest-helper
Version: 0.7.1
Summary: This is my mixiu pytest helper package
Home-page: https://github.com/ckf10000/mixiu-pytest-helper
Author: ckf10000
Author-email: ckf10000@sina.com
Classifier: Programming Language :: Python :: 3
Classifier: License :: OSI Approved :: MIT License
Classifier: Operating System :: OS Independent
License-File: LICENSE
Requires-Dist: pytest >=8.3.1
Requires-Dist: pandas >=2.2.2
Requires-Dist: pytest-cov >=5.0.0
Requires-Dist: pytest-html >=4.1.1
Requires-Dist: allure-pytest >=2.13.5
Requires-Dist: mixiu-app-helper >=0.2.4
Requires-Dist: catlive-app-helper >=0.0.8
Requires-Dist: pytest-json-report >=1.5.0
Requires-Dist: distributed-logging >=0.0.3
Requires-Dist: python-apollo-proxy >=0.1.8
Requires-Dist: middleware-help-python >=0.1.3
